super_devops/__init__.py
super_devops/utils.py
super_devops/container/__init__.py
super_devops/container/docker_wrapper.py
super_devops/container/registry_wrapper.py
super_devops/database/__init__.py
super_devops/database/sqlalchemy_wrapper.py
super_devops/firewall/__init__.py
super_devops/firewall/iptables_wrapper.py
super_devops/gitlab/__init__.py
super_devops/grafana_stack/__init__.py
super_devops/grafana_stack/grafana_wrapper.py
super_devops/grafana_stack/loki_wrapper.py
super_devops/jenkins/__init__.py
super_devops/ldap/__init__.py
super_devops/ldap/ldap3_wrapper.py
super_devops/misc/__init__.py
super_devops/misc/colorama_wrapper.py
super_devops/nagios/__init__.py
super_devops/nagios/nagios_wrapper.py
super_devops/network/__init__.py
super_devops/network/network_wrapper.py
super_devops/nosql/__init__.py
super_devops/nosql/mongo_wrapper.py
super_devops/nosql/redis_wrapper.py
super_devops/office/__init__.py
super_devops/rabbitmq/__init__.py
super_devops/rabbitmq/pika_wrapper.py
super_devops/rabbitmq/rabbitmq_wrapper.py
super_devops/super_email/__init__.py
super_devops/super_email/smtplib_wrapper.py
super_devops/super_ftp/__init__.py
super_devops/super_http/__init__.py
super_devops/super_http/requests_wrapper.py
super_devops/super_log/__init__.py
super_devops/super_log/logging_wrapper.py
super_devops/super_nfs/__init__.py
super_devops/super_rf/__init__.py
super_devops/super_rf/cache.py
super_devops/super_rf/listener.py
super_devops/super_rf/rf_wrapper.py
super_devops/super_rf/unittest_wrapper.py
super_devops/super_rf/utils.py
super_devops/super_selenium/__init__.py
super_devops/super_selenium/button.py
super_devops/super_selenium/checkbox.py
super_devops/super_selenium/combo.py
super_devops/super_selenium/element_locator.py
super_devops/super_selenium/frame.py
super_devops/super_selenium/label.py
super_devops/super_selenium/link.py
super_devops/super_selenium/selenium_wrapper.py
super_devops/super_selenium/table.py
super_devops/super_selenium/textbox.py
super_devops-1.9.2.dist-info/AUTHORS.rst
super_devops-1.9.2.dist-info/LICENSE
super_devops-1.9.2.dist-info/METADATA
super_devops-1.9.2.dist-info/WHEEL
super_devops-1.9.2.dist-info/top_level.txt
super_devops-1.9.2.dist-info/RECORD
