Metadata-Version: 2.1
Name: super-devops
Version: 1.9.2
Summary: Tons of devops tools used for testing, monitoring, logging...
Home-page: https://github.com/crazy-canux/super-devops
Author: Canux CHENG
Author-email: canuxcheng@gmail.com
Maintainer: Canux CHENG
Maintainer-email: canuxcheng@gmail.com
License: GPL
Keywords: DevOps Monitoring Testing Logging
Platform: any
Classifier: Development Status :: 5 - Production/Stable
Classifier: Environment :: Other Environment
Classifier: Intended Audience :: Developers
Classifier: Natural Language :: English
Classifier: License :: OSI Approved :: GNU General Public License (GPL)
Classifier: Operating System :: POSIX
Classifier: Programming Language :: Python
Classifier: Programming Language :: Python :: 3
Classifier: Programming Language :: Python :: 3.5
Classifier: Programming Language :: Python :: 3.6
Classifier: Programming Language :: Python :: 3.7
Classifier: Programming Language :: Python :: 3.8
Classifier: Topic :: Software Development :: Libraries
